jik_app/__init__.py
jik_app/py.typed
jik_server/__init__.py
jik_server/py.typed
starlette/__init__.py
starlette/_compat.py
starlette/_exception_handler.py
starlette/_utils.py
starlette/applications.py
starlette/authentication.py
starlette/background.py
starlette/concurrency.py
starlette/config.py
starlette/convertors.py
starlette/datastructures.py
starlette/endpoints.py
starlette/exceptions.py
starlette/formparsers.py
starlette/middleware/__init__.py
starlette/middleware/authentication.py
starlette/middleware/base.py
starlette/middleware/cors.py
starlette/middleware/errors.py
starlette/middleware/exceptions.py
starlette/middleware/gzip.py
starlette/middleware/httpsredirect.py
starlette/middleware/sessions.py
starlette/middleware/trustedhost.py
starlette/middleware/wsgi.py
starlette/py.typed
starlette/requests.py
starlette/responses.py
starlette/routing.py
starlette/schemas.py
starlette/staticfiles.py
starlette/status.py
starlette/templating.py
starlette/testclient.py
starlette/types.py
starlette/websockets.py
uvicorn/__init__.py
uvicorn/__main__.py
uvicorn/_subprocess.py
uvicorn/_types.py
uvicorn/config.py
uvicorn/importer.py
uvicorn/lifespan/__init__.py
uvicorn/lifespan/off.py
uvicorn/lifespan/on.py
uvicorn/logging.py
uvicorn/loops/__init__.py
uvicorn/loops/asyncio.py
uvicorn/loops/auto.py
uvicorn/loops/uvloop.py
uvicorn/main.py
uvicorn/middleware/__init__.py
uvicorn/middleware/asgi2.py
uvicorn/middleware/message_logger.py
uvicorn/middleware/proxy_headers.py
uvicorn/middleware/wsgi.py
uvicorn/protocols/__init__.py
uvicorn/protocols/http/__init__.py
uvicorn/protocols/http/auto.py
uvicorn/protocols/http/flow_control.py
uvicorn/protocols/http/h11_impl.py
uvicorn/protocols/http/httptools_impl.py
uvicorn/protocols/utils.py
uvicorn/protocols/websockets/__init__.py
uvicorn/protocols/websockets/auto.py
uvicorn/protocols/websockets/websockets_impl.py
uvicorn/protocols/websockets/wsproto_impl.py
uvicorn/py.typed
uvicorn/server.py
uvicorn/supervisors/__init__.py
jik-0.0.2.dist-info/METADATA
jik-0.0.2.dist-info/WHEEL
jik-0.0.2.dist-info/RECORD
